library_name/__init__.py
core_cmd-0.0.0.dist-info/LICENSE
core_cmd-0.0.0.dist-info/METADATA
core_cmd-0.0.0.dist-info/WHEEL
core_cmd-0.0.0.dist-info/top_level.txt
core_cmd-0.0.0.dist-info/RECORD
